memento/__init__.py
memento/caching.py
memento/configurations.py
memento/exceptions.py
memento/memento.py
memento/notifications.py
memento/parallel.py
memento/task_interface.py
memento_ml-1.2.0.dist-info/LICENSE
memento_ml-1.2.0.dist-info/METADATA
memento_ml-1.2.0.dist-info/WHEEL
memento_ml-1.2.0.dist-info/top_level.txt
memento_ml-1.2.0.dist-info/RECORD
