Metadata-Version: 2.1
Name: memento-ml
Version: 1.2.0
Summary: A Python library for running computationally expensive experiments
Author-email: Wickerlab dev team <luke.x.chang@gmail.com>
License: BSD 3-Clause License
Project-URL: Homepage, https://github.com/wickerlab/memento
Keywords: experiment,parallel,sklearn,machine learning
Classifier: License :: OSI Approved :: BSD License
Classifier: Programming Language :: Python :: 3
Classifier: Programming Language :: Python :: 3.8
Classifier: Programming Language :: Python :: 3.9
Classifier: Programming Language :: Python :: 3.10
Classifier: Programming Language :: Python :: 3.11
Requires-Python: >=3.8
License-File: LICENSE
Requires-Dist: cloudpickle ~=2.2.1
Requires-Dist: networkx ~=3.1
Requires-Dist: pandas ~=2.0.1
Requires-Dist: pandas-stubs
Provides-Extra: dev
Requires-Dist: black ; extra == 'dev'
Requires-Dist: pylint ; extra == 'dev'
Requires-Dist: bumpver ; extra == 'dev'
Requires-Dist: isort ; extra == 'dev'
Requires-Dist: pip-tools ; extra == 'dev'
Requires-Dist: pytest ; extra == 'dev'
Requires-Dist: Sphinx ; extra == 'dev'
Requires-Dist: mypy ; extra == 'dev'
Requires-Dist: aiosmtpd ; extra == 'dev'
Requires-Dist: scikit-learn ; extra == 'dev'
